Reduino/__init__.py
Reduino/Actuators/Buzzer.py
Reduino/Actuators/DCMotor.py
Reduino/Actuators/Led.py
Reduino/Actuators/RGBLed.py
Reduino/Actuators/Servo.py
Reduino/Actuators/__init__.py
Reduino/Communication/SerialMonitor.py
Reduino/Communication/__init__.py
Reduino/Core/__init__.py
Reduino/Displays/LCD.py
Reduino/Displays/__init__.py
Reduino/Sensors/Button.py
Reduino/Sensors/Potentiometer.py
Reduino/Sensors/Ultrasonic.py
Reduino/Sensors/__init__.py
Reduino/Utils/__init__.py
Reduino/toolchain/pio.py
Reduino/transpile/__init__.py
Reduino/transpile/ast.py
Reduino/transpile/emitter.py
Reduino/transpile/parser.py
reduino-1.2.0.dist-info/licenses/LICENSE
reduino-1.2.0.dist-info/METADATA
reduino-1.2.0.dist-info/WHEEL
reduino-1.2.0.dist-info/top_level.txt
reduino-1.2.0.dist-info/RECORD
