Metadata-Version: 2.4
Name: Reduino
Version: 1.2.0
Summary: Reduino transpiles Python scripts into efficient Arduino C++ and uploads automatically. A simple, intuitive way to control sensors, LEDs, and actuators without touching C++.
Author-email: Arnav Bajaj <arnavbajaj9@gmail.com>
License-Expression: GPL-3.0-or-later
Project-URL: Homepage, https://github.com/Jackhammer9/Reduino
Project-URL: Issues, https://github.com/Jackhammer9/Reduino/issues
Keywords: arduino,embedded,transpiler,robotics,avr,cpp
Classifier: Development Status :: 5 - Production/Stable
Classifier: Programming Language :: Python :: 3
Classifier: Programming Language :: Python :: 3.11
Classifier: Operating System :: OS Independent
Classifier: Topic :: Software Development :: Code Generators
Classifier: Topic :: Software Development :: Embedded Systems
Requires-Python: >=3.10
License-File: LICENSE
Requires-Dist: pyserial
Dynamic: license-file
